AUTHORS.rst
HISTORY.rst
LICENSE
MANIFEST.in
README.rst
requirements.txt
setup.py
rcquerybuilder/__init__.py
rcquerybuilder/builder.py
rcquerybuilder/core.py
rcquerybuilder/helpers.py
rcquerybuilder/pipeline.py
rcquerybuilder.egg-info/PKG-INFO
rcquerybuilder.egg-info/SOURCES.txt
rcquerybuilder.egg-info/dependency_links.txt
rcquerybuilder.egg-info/not-zip-safe
rcquerybuilder.egg-info/requires.txt
rcquerybuilder.egg-info/top_level.txt