Metadata-Version: 1.1
Name: rcquerybuilder
Version: 0.1.2
Summary: Provides a fluent query builder wrapper around pymongo
Home-page: http://github.com/red-crown/mongo-querybuilder/
Author: Matthew Strickland
Author-email: matthew@redcrown.co
License: The MIT License (MIT)
